Metadata-Version: 1.0
Name: soinlocal
Version: 0.1.3
Summary: so.com
Home-page: https://github.com/ghubgituse/so.git
Author: git
Author-email: usegithub@126.com
License: MIT Licence
Keywords: pip,server,so
Platform: any
